{
  "resourceType" : "Parameters",
  "id" : "AnemiaScreeningParameters",
  "parameter" : [{
    "name" : "subject",
    "valueString" : "Patient/Patient1"
  },
  {
    "name" : "practitioner",
    "valueString" : "Practitioner/Practitioner1"
  },
  {
    "name" : "encounter",
    "valueString" : "Encounter/Encounter1"
  },
  {
    "name" : "planDefinition",
    "resource" : {
      "resourceType" : "PlanDefinition",
      "id" : "AnemiaScreeningPlan",
      "meta" : {
        "profile" : ["http://hl7.org/fhir/uv/cpg/StructureDefinition/cpg-computableplandefinition"]
      },
      "extension" : [{
        "url" : "http://hl7.org/fhir/uv/cpg/StructureDefinition/cpg-knowledgeCapability",
        "valueCode" : "publishable"
      },
      {
        "url" : "http://hl7.org/fhir/uv/cpg/StructureDefinition/cpg-knowledgeRepresentationLevel",
        "valueCode" : "structured"
      }],
      "url" : "http://example.org/PlanDefinition/AnemiaScreeningPlan",
      "version" : "0.1.0",
      "name" : "AnemiaScreeningPlan",
      "title" : "PlanDefinition AnemiaScreeningPlan",
      "type" : {
        "coding" : [{
          "system" : "http://terminology.hl7.org/CodeSystem/plan-definition-type",
          "code" : "clinical-protocol",
          "display" : "Clinical Protocol"
        }]
      },
      "status" : "draft",
      "experimental" : true,
      "publisher" : "Example",
      "description" : "Definition of plan to screen for iron defeciency anemia",
      "jurisdiction" : [{
        "coding" : [{
          "system" : "http://unstats.un.org/unsd/methods/m49/m49.htm",
          "code" : "001",
          "display" : "World"
        }]
      }],
      "library" : ["http://example.org/Library/AnemiaScreeningLibrary"],
      "action" : [{
        "title" : "Order CBC Lab Panel",
        "description" : "Order CBC Lab Panel to screen for anemia",
        "code" : [{
          "coding" : [{
            "system" : "http://hl7.org/fhir/uv/cpg/CodeSystem/cpg-common-process",
            "code" : "diagnostic-testing",
            "display" : "Conduct Diagnostic Tests"
          }]
        }],
        "condition" : [{
          "kind" : "applicability",
          "expression" : {
            "language" : "text/cql-identifier",
            "expression" : "Needs CBC"
          }
        }]
      },
      {
        "title" : "Order serum ferritin",
        "description" : "Order serum ferritin to monitor iron status",
        "code" : [{
          "coding" : [{
            "system" : "http://hl7.org/fhir/uv/cpg/CodeSystem/cpg-common-process",
            "code" : "diagnostic-testing",
            "display" : "Conduct Diagnostic Tests"
          }]
        }],
        "condition" : [{
          "kind" : "applicability",
          "expression" : {
            "language" : "text/cql-identifier",
            "expression" : "Needs serum ferritin"
          }
        }]
      }]
    }
  },
  {
    "name" : "data",
    "resource" : {
      "resourceType" : "Bundle",
      "id" : "PatientTestBundle1",
      "type" : "collection",
      "entry" : [{
        "resource" : {
          "resourceType" : "Patient",
          "id" : "Patient1",
          "name" : [{
            "given" : ["Alice"]
          }]
        }
      },
      {
        "resource" : {
          "resourceType" : "Encounter",
          "id" : "Encounter1",
          "status" : "in-progress",
          "class" : {
            "system" : "http://terminology.hl7.org/CodeSystem/v3-ActCode",
            "code" : "AMB"
          },
          "subject" : {
            "reference" : "Patient/Patient1"
          },
          "participant" : [{
            "individual" : {
              "reference" : "Practitioner/Practitioner1"
            }
          }]
        }
      },
      {
        "resource" : {
          "resourceType" : "Practitioner",
          "id" : "Practitioner1",
          "name" : [{
            "given" : ["Michael"]
          }]
        }
      },
      {
        "resource" : {
          "resourceType" : "MedicationRequest",
          "id" : "PastMedicationRequest",
          "status" : "active",
          "intent" : "order",
          "medicationCodeableConcept" : {
            "text" : "Some medication"
          },
          "subject" : {
            "reference" : "Patient/Patient1"
          },
          "authoredOn" : "2023-01-01"
        }
      },
      {
        "resource" : {
          "resourceType" : "Medication",
          "id" : "CurrentMedication",
          "status" : "active"
        }
      },
      {
        "resource" : {
          "resourceType" : "Medication",
          "id" : "PastMedication",
          "status" : "inactive",
          "form" : {
            "coding" : [{
              "system" : "http://snomed.info/sct",
              "code" : "pill",
              "display" : "Pill"
            }]
          }
        }
      },
      {
        "resource" : {
          "resourceType" : "DetectedIssue",
          "id" : "DetectedIssue1",
          "status" : "final",
          "code" : {
            "coding" : [{
              "system" : "http://terminology.hl7.org/CodeSystem/v3-ActCode",
              "code" : "TIME",
              "display" : "Time-related Detected Issue"
            }]
          },
          "severity" : "high",
          "patient" : {
            "reference" : "Patient/Patient1"
          },
          "identifiedDateTime" : "2023-01-01"
        }
      },
      {
        "resource" : {
          "resourceType" : "Condition",
          "id" : "Condition1",
          "clinicalStatus" : {
            "coding" : [{
              "system" : "http://terminology.hl7.org/CodeSystem/condition-clinical",
              "code" : "active"
            }]
          },
          "verificationStatus" : {
            "coding" : [{
              "system" : "http://terminology.hl7.org/CodeSystem/condition-ver-status",
              "code" : "provisional"
            }]
          },
          "category" : [{
            "coding" : [{
              "system" : "http://terminology.hl7.org/CodeSystem/condition-category",
              "code" : "problem-list-item"
            }]
          }],
          "code" : {
            "coding" : [{
              "system" : "http://snomed.info/sct",
              "code" : "422504002",
              "display" : "Ischemic stroke (disorder)"
            }]
          },
          "subject" : {
            "reference" : "Patient/Patient1"
          },
          "recordedDate" : "2023-01-01"
        }
      },
      {
        "resource" : {
          "resourceType" : "Observation",
          "id" : "Inference1",
          "status" : "final",
          "code" : {
            "coding" : [{
              "system" : "http://snomed.info/sct",
              "code" : "448765001",
              "display" : "Unintentional weight loss (finding)"
            }],
            "text" : "Inference"
          },
          "subject" : {
            "reference" : "Patient/Patient1"
          },
          "effectiveDateTime" : "2023-01-01"
        }
      },
      {
        "resource" : {
          "resourceType" : "Flag",
          "id" : "Flag1",
          "status" : "active",
          "category" : [{
            "coding" : [{
              "system" : "http://terminology.hl7.org/CodeSystem/flag-category",
              "code" : "admin",
              "display" : "Administrative"
            }]
          }],
          "code" : {
            "text" : "Flag"
          },
          "subject" : {
            "reference" : "Patient/Patient1"
          },
          "period" : {
            "start" : "2023-01-01",
            "end" : "2024-01-01"
          }
        }
      }]
    }
  }]
}